fds/__init__.py
fds/sdk/__init__.py
fds/sdk/OpenFactSetMarketplace/__init__.py
fds/sdk/OpenFactSetMarketplace/api_client.py
fds/sdk/OpenFactSetMarketplace/configuration.py
fds/sdk/OpenFactSetMarketplace/exceptions.py
fds/sdk/OpenFactSetMarketplace/model_utils.py
fds/sdk/OpenFactSetMarketplace/rest.py
fds/sdk/OpenFactSetMarketplace/api/__init__.py
fds/sdk/OpenFactSetMarketplace/api/partners_api.py
fds/sdk/OpenFactSetMarketplace/api/products_api.py
fds/sdk/OpenFactSetMarketplace/apis/__init__.py
fds/sdk/OpenFactSetMarketplace/model/__init__.py
fds/sdk/OpenFactSetMarketplace/model/attributes_groups_item.py
fds/sdk/OpenFactSetMarketplace/model/documents_items.py
fds/sdk/OpenFactSetMarketplace/model/error.py
fds/sdk/OpenFactSetMarketplace/model/error_response.py
fds/sdk/OpenFactSetMarketplace/model/meta.py
fds/sdk/OpenFactSetMarketplace/model/meta_pagination.py
fds/sdk/OpenFactSetMarketplace/model/partner.py
fds/sdk/OpenFactSetMarketplace/model/partner_address.py
fds/sdk/OpenFactSetMarketplace/model/partner_social_media.py
fds/sdk/OpenFactSetMarketplace/model/partner_success_response.py
fds/sdk/OpenFactSetMarketplace/model/partners_success_response.py
fds/sdk/OpenFactSetMarketplace/model/product.py
fds/sdk/OpenFactSetMarketplace/model/product_partner.py
fds/sdk/OpenFactSetMarketplace/model/product_success_response.py
fds/sdk/OpenFactSetMarketplace/model/products_success_response.py
fds/sdk/OpenFactSetMarketplace/model/related_products.py
fds/sdk/OpenFactSetMarketplace/model/third_party_urls.py
fds/sdk/OpenFactSetMarketplace/models/__init__.py
fds.sdk.OpenFactSetMarketplace-3.0.0.dist-info/LICENSE
fds.sdk.OpenFactSetMarketplace-3.0.0.dist-info/METADATA
fds.sdk.OpenFactSetMarketplace-3.0.0.dist-info/WHEEL
fds.sdk.OpenFactSetMarketplace-3.0.0.dist-info/top_level.txt
fds.sdk.OpenFactSetMarketplace-3.0.0.dist-info/RECORD
